[
  {
    "id": "1",
    "name": "Kardio",
    "type": "personalni",
    "facilityId": "1",
    "duration": {
      "start": "09:00:00",
      "end": "10:00:00"
    },
    "coachId": "1",
    "description": "Veoma zanimljiv i jak trening!",
    "image": "bascelik.jpg",
    "price": 2000
  },
  {
    "id": "2",
    "name": "Hipertrofija",
    "type": "grupni",
    "facilityId": "2",
    "duration": {
      "start": "17:00:00",
      "end": "18:00:00"
    },
    "coachId": "1",
    "description": "Lake tezine!",
    "image": "bascelik.jpg",
    "price": 3000
  }
]